keyboard_extended/KeyboardClass.py
keyboard_extended/__init__.py
keyboard_extended/keyboard_extended.py
keyboard_extended-0.2.4.dist-info/LICENSE
keyboard_extended-0.2.4.dist-info/METADATA
keyboard_extended-0.2.4.dist-info/WHEEL
keyboard_extended-0.2.4.dist-info/top_level.txt
keyboard_extended-0.2.4.dist-info/RECORD
