Metadata-Version: 2.1
Name: keyboard-extended
Version: 0.2.4
Summary: Extension for the keyboard package
Author: André Herber
Author-email: andre.herber.programming@gmail.com
Keywords: python
Classifier: Development Status :: 1 - Planning
Classifier: Intended Audience :: Developers
Classifier: Programming Language :: Python :: 3
Classifier: Programming Language :: Python :: 3.9
Classifier: Programming Language :: Python :: 3.10
Classifier: License :: OSI Approved :: MIT License
Classifier: Operating System :: Microsoft :: Windows
License-File: LICENSE
Requires-Dist: keyboard
